setup.py
dftcp/__init__.py
dftcp/tcp_protocol.py
dftcp.egg-info/PKG-INFO
dftcp.egg-info/SOURCES.txt
dftcp.egg-info/dependency_links.txt
dftcp.egg-info/requires.txt
dftcp.egg-info/top_level.txt