Metadata-Version: 1.1
Name: dftcp
Version: 0.0.1
Summary: Tcp templates for dataforge (http://npm.mipt.ru/dataforge/)
Home-page: https://github.com/kapot65/python-df-tcp
Author: Vasilii Chernov
Author-email: kapot65@gmail.com
License: UNKNOWN
Download-URL: https://github.com/kapot65/python-df-tcp/tarball/0.0.1
Keywords: dataforge
Platform: UNKNOWN
